odoo/addons/easy_my_coop/README.rst
odoo/addons/easy_my_coop/__init__.py
odoo/addons/easy_my_coop/__manifest__.py
odoo/addons/easy_my_coop/data/easy_my_coop_data.xml
odoo/addons/easy_my_coop/data/mail_template_data.xml
odoo/addons/easy_my_coop/data/paperformat.xml
odoo/addons/easy_my_coop/demo/coop.xml
odoo/addons/easy_my_coop/demo/users.xml
odoo/addons/easy_my_coop/i18n/ca_ES.po
odoo/addons/easy_my_coop/i18n/easy_my_coop.pot
odoo/addons/easy_my_coop/i18n/es.po
odoo/addons/easy_my_coop/i18n/fr.po
odoo/addons/easy_my_coop/i18n/fr_BE.po
odoo/addons/easy_my_coop/i18n/nl_BE.po
odoo/addons/easy_my_coop/migrations/12.0.3.1.0/pre-migration.py
odoo/addons/easy_my_coop/migrations/8.0.1.0/pre-migration.py
odoo/addons/easy_my_coop/models/__init__.py
odoo/addons/easy_my_coop/models/account_invoice.py
odoo/addons/easy_my_coop/models/account_journal.py
odoo/addons/easy_my_coop/models/company.py
odoo/addons/easy_my_coop/models/mail_template.py
odoo/addons/easy_my_coop/models/operation_request.py
odoo/addons/easy_my_coop/models/partner.py
odoo/addons/easy_my_coop/models/product.py
odoo/addons/easy_my_coop/models/res_partner_bank.py
odoo/addons/easy_my_coop/models/share_line.py
odoo/addons/easy_my_coop/models/subscription_register.py
odoo/addons/easy_my_coop/models/subscription_request.py
odoo/addons/easy_my_coop/readme/CONTRIBUTORS.rst
odoo/addons/easy_my_coop/readme/DESCRIPTION.rst
odoo/addons/easy_my_coop/readme/INSTALL.rst
odoo/addons/easy_my_coop/readme/ROADMAP.rst
odoo/addons/easy_my_coop/report/__init__.py
odoo/addons/easy_my_coop/report/account_invoice_report.py
odoo/addons/easy_my_coop/report/cooperator_certificat_G001.xml
odoo/addons/easy_my_coop/report/cooperator_invoice_G002.xml
odoo/addons/easy_my_coop/report/cooperator_register_G001.xml
odoo/addons/easy_my_coop/report/cooperator_subscription_G001.xml
odoo/addons/easy_my_coop/report/easy_my_coop_report.xml
odoo/addons/easy_my_coop/report/layout.xml
odoo/addons/easy_my_coop/security/ir.model.access.csv
odoo12_addon_easy_my_coop-12.0.3.3.0.dist-info/METADATA
odoo12_addon_easy_my_coop-12.0.3.3.0.dist-info/WHEEL
odoo12_addon_easy_my_coop-12.0.3.3.0.dist-info/top_level.txt
odoo12_addon_easy_my_coop-12.0.3.3.0.dist-info/RECORD
