Metadata-Version: 2.1
Name: odoo12-addon-easy-my-coop
Version: 12.0.3.3.0
Summary: Manage your cooperative shares
Home-page: https://coopiteasy.be
Author: Coop IT Easy SCRLfs
License: AGPL-3
Platform: UNKNOWN
Classifier: Programming Language :: Python
Classifier: Framework :: Odoo
Classifier: Framework :: Odoo :: 12.0
Classifier: License :: OSI Approved :: GNU Affero General Public License v3
Requires-Python: >=3.5
Requires-Dist: odoo12-addon-email-template-config
Requires-Dist: odoo12-addon-partner-age
Requires-Dist: odoo12-addon-partner-contact-address
Requires-Dist: odoo12-addon-partner-contact-birthdate
Requires-Dist: odoo12-addon-partner-contact-gender
Requires-Dist: odoo12-addon-partner-firstname
Requires-Dist: odoo (<12.1dev,>=12.0a)
